gcf_dev_gen/__init__.py
gcf_dev_gen/cli.py
gcf_dev_gen/gcf_dev_gen.py
gcf_dev_gen-0.1.1.dist-info/AUTHORS.rst
gcf_dev_gen-0.1.1.dist-info/LICENSE
gcf_dev_gen-0.1.1.dist-info/METADATA
gcf_dev_gen-0.1.1.dist-info/WHEEL
gcf_dev_gen-0.1.1.dist-info/entry_points.txt
gcf_dev_gen-0.1.1.dist-info/top_level.txt
gcf_dev_gen-0.1.1.dist-info/RECORD
