Metadata-Version: 2.1
Name: gcf-dev-gen
Version: 0.1.1
Summary: GCF dev generator
Home-page: https://github.com/aitaro/gcf_dev_gen
Author: Aitaro Chaya
Author-email: aitaro.chaya@gmail.com
License: MIT license
Keywords: gcf_dev_gen
Platform: UNKNOWN
Classifier: Development Status :: 2 - Pre-Alpha
Classifier: Intended Audience :: Developers
Classifier: License :: OSI Approved :: MIT License
Classifier: Natural Language :: English
Classifier: Programming Language :: Python :: 3
Classifier: Programming Language :: Python :: 3.5
Classifier: Programming Language :: Python :: 3.6
Classifier: Programming Language :: Python :: 3.7
Classifier: Programming Language :: Python :: 3.8
Requires-Python: >=3.5
Requires-Dist: Click (>=7.0)
